podcast_player/__init__.py
podcast_player/cli.py
podcast_player/database.py
podcast_player/database_manager.py
podcast_player/podcast.py
podcast_player/podcast_parser.py
podcast_player/podcast_player.py
podcast_player/user_settings.py
podcast_player-1.6.1.dist-info/METADATA
podcast_player-1.6.1.dist-info/WHEEL
podcast_player-1.6.1.dist-info/entry_points.txt
podcast_player-1.6.1.dist-info/top_level.txt
podcast_player-1.6.1.dist-info/RECORD
