Metadata-Version: 2.1
Name: podcast-player
Version: 1.6.1
Summary: A Python command line podcast player.
Home-page: https://github.com/aziezahmed/podcast-player
Author: Aziez Ahmed Chawdhary
Author-email: 
License: MIT License
Keywords: cli,audio,podcast,stream
Platform: UNKNOWN
Classifier: Intended Audience :: Developers
Classifier: Topic :: Utilities
Classifier: License :: Public Domain
Classifier: Natural Language :: English
Classifier: Operating System :: OS Independent
Classifier: Environment :: Console
Classifier: Programming Language :: Python :: 2
Classifier: Programming Language :: Python :: 2.6
Classifier: Programming Language :: Python :: 2.7
Classifier: Programming Language :: Python :: 3
Classifier: Programming Language :: Python :: 3.2
Classifier: Programming Language :: Python :: 3.3
Classifier: Programming Language :: Python :: 3.4
Classifier: Programming Language :: Python :: 3.5
Classifier: Programming Language :: Python :: 3.6
Requires-Dist: docopt
Requires-Dist: pyinquirer
Requires-Dist: feedparser
Requires-Dist: listparser
Requires-Dist: sqlobject
Requires-Dist: configparser
Requires-Dist: python-dateutil
Provides-Extra: test
Requires-Dist: coverage ; extra == 'test'
Requires-Dist: pytest ; extra == 'test'
Requires-Dist: pytest-cov ; extra == 'test'
